bluepyopt/__init__.py
bluepyopt/api.py
bluepyopt/evaluators.py
bluepyopt/objectives.py
bluepyopt/optimisations.py
bluepyopt/parameters.py
bluepyopt/stoppingCriteria.py
bluepyopt/tools.py
bluepyopt/deapext/CMA_MO.py
bluepyopt/deapext/CMA_SO.py
bluepyopt/deapext/__init__.py
bluepyopt/deapext/algorithms.py
bluepyopt/deapext/hype.py
bluepyopt/deapext/optimisations.py
bluepyopt/deapext/optimisationsCMA.py
bluepyopt/deapext/stoppingCriteria.py
bluepyopt/deapext/utils.py
bluepyopt/deapext/tools/__init__.py
bluepyopt/deapext/tools/selIBEA.py
bluepyopt/ephys/__init__.py
bluepyopt/ephys/acc.py
bluepyopt/ephys/base.py
bluepyopt/ephys/create_acc.py
bluepyopt/ephys/create_hoc.py
bluepyopt/ephys/efeatures.py
bluepyopt/ephys/evaluators.py
bluepyopt/ephys/extra_features_utils.py
bluepyopt/ephys/locations.py
bluepyopt/ephys/mechanisms.py
bluepyopt/ephys/models.py
bluepyopt/ephys/morphologies.py
bluepyopt/ephys/objectives.py
bluepyopt/ephys/objectivescalculators.py
bluepyopt/ephys/parameters.py
bluepyopt/ephys/protocols.py
bluepyopt/ephys/recordings.py
bluepyopt/ephys/responses.py
bluepyopt/ephys/serializer.py
bluepyopt/ephys/simulators.py
bluepyopt/ephys/stimuli.py
bluepyopt/ephys/examples/__init__.py
bluepyopt/ephys/examples/simplecell/__init__.py
bluepyopt/ephys/examples/simplecell/simple.swc
bluepyopt/ephys/examples/simplecell/simplecell.py
bluepyopt/ephys/parameterscalers/__init__.py
bluepyopt/ephys/parameterscalers/acc_iexpr.py
bluepyopt/ephys/parameterscalers/parameterscalers.py
bluepyopt/ephys/static/arbor_mechanisms.json
bluepyopt/ephys/templates/cell_template.jinja2
bluepyopt/ephys/templates/acc/_json_template.jinja2
bluepyopt/ephys/templates/acc/decor_acc_template.jinja2
bluepyopt/ephys/templates/acc/label_dict_acc_template.jinja2
bluepyopt/ipyp/__init__.py
bluepyopt/ipyp/bpopt_tasksdb.py
bluepyopt/neuroml/__init__.py
bluepyopt/neuroml/biophys.py
bluepyopt/neuroml/cell.py
bluepyopt/neuroml/morphology.py
bluepyopt/neuroml/simulation.py
bluepyopt-1.14.17.dist-info/AUTHORS.txt
bluepyopt-1.14.17.dist-info/COPYING
bluepyopt-1.14.17.dist-info/COPYING.lesser
bluepyopt-1.14.17.dist-info/LICENSE.txt
bluepyopt-1.14.17.dist-info/METADATA
bluepyopt-1.14.17.dist-info/WHEEL
bluepyopt-1.14.17.dist-info/entry_points.txt
bluepyopt-1.14.17.dist-info/top_level.txt
bluepyopt-1.14.17.dist-info/RECORD
